{
  "name": "Details",
  "settings": {
    "strict": false,
    "forceId": false,
    "replaceOnPUT": true,
    "idInjection": false,
    "mysql": {
      "schema": "db1",
      "table": "details"
    }
  },
  "properties": {
    "id": {
      "type": "string",
      "id": 1,
      "required": false,
      "length": 36,
      "precision": null,
      "scale": null,
      "mysql": {
        "columnName": "id",
        "dataType": "varchar",
        "dataLength": 36,
        "dataPrecision": null,
        "dataScale": null,
        "nullable": "N"
      },
      "updateOnly": false
    },
    "name": {
      "type": "string",
      "required": true,
      "length": 100,
      "precision": null,
      "scale": null,
      "mysql": {
        "columnName": "name",
        "dataType": "varchar",
        "dataLength": 100,
        "dataPrecision": null,
        "dataScale": null,
        "nullable": "N"
      }
    },
    "mobile": {
      "type": "string",
      "required": true,
      "length": 4294967295,
      "precision": null,
      "scale": null,
      "mysql": {
        "columnName": "mobile",
        "dataType": "longtext",
        "dataLength": 4294967295,
        "dataPrecision": null,
        "dataScale": null,
        "nullable": "N"
      }
    },
    "address": {
      "type": "string",
      "required": false,
      "length": 4294967295,
      "precision": null,
      "scale": null,
      "mysql": {
        "columnName": "address",
        "dataType": "longtext",
        "dataLength": 4294967295,
        "dataPrecision": null,
        "dataScale": null,
        "nullable": "N"
      }
    },
    "state": {
      "type": "string",
      "required": false,
      "length": 30,
      "precision": null,
      "scale": null,
      "mysql": {
        "columnName": "state",
        "dataType": "varchar",
        "dataLength": 30,
        "dataPrecision": null,
        "dataScale": null,
        "nullable": "N"
      }
    },
    "city": {
      "type": "string",
      "required": false,
      "length": 30,
      "precision": null,
      "scale": null,
      "mysql": {
        "columnName": "city",
        "dataType": "varchar",
        "dataLength": 30,
        "dataPrecision": null,
        "dataScale": null,
        "nullable": "N"
      }
    },
    "statecode": {
      "type": "number",
      "required": false,
      "length": null,
      "precision": 10,
      "scale": 0,
      "mysql": {
        "columnName": "stateCode",
        "dataType": "int",
        "dataLength": null,
        "dataPrecision": 10,
        "dataScale": 0,
        "nullable": "N"
      }
    },
    "gstin": {
      "type": "string",
      "required": false,
      "length": 30,
      "precision": null,
      "scale": null,
      "mysql": {
        "columnName": "gstin",
        "dataType": "varchar",
        "dataLength": 30,
        "dataPrecision": null,
        "dataScale": null,
        "nullable": "N"
      }
    },
    "bankaccountno": {
      "type": "string",
      "required": false,
      "length": 30,
      "precision": null,
      "scale": null,
      "mysql": {
        "columnName": "bankAccountNo",
        "dataType": "varchar",
        "dataLength": 30,
        "dataPrecision": null,
        "dataScale": null,
        "nullable": "N"
      }
    },
    "bankaccountname": {
      "type": "string",
      "required": false,
      "length": 4294967295,
      "precision": null,
      "scale": null,
      "mysql": {
        "columnName": "bankAccountName",
        "dataType": "longtext",
        "dataLength": 4294967295,
        "dataPrecision": null,
        "dataScale": null,
        "nullable": "N"
      }
    },
    "bankname": {
      "type": "string",
      "required": false,
      "length": 4294967295,
      "precision": null,
      "scale": null,
      "mysql": {
        "columnName": "bankName",
        "dataType": "longtext",
        "dataLength": 4294967295,
        "dataPrecision": null,
        "dataScale": null,
        "nullable": "N"
      }
    },
    "bankifsc": {
      "type": "string",
      "required": false,
      "length": 20,
      "precision": null,
      "scale": null,
      "mysql": {
        "columnName": "bankIFSC",
        "dataType": "varchar",
        "dataLength": 20,
        "dataPrecision": null,
        "dataScale": null,
        "nullable": "N"
      }
    },
    "termsandconditions": {
      "type": "string",
      "required": false,
      "length": 4294967295,
      "precision": null,
      "scale": null,
      "mysql": {
        "columnName": "termsAndConditions",
        "dataType": "longtext",
        "dataLength": 4294967295,
        "dataPrecision": null,
        "dataScale": null,
        "nullable": "N"
      }
    },
    "logo": {
      "type": "string",
      "required": false,
      "length": 4294967295,
      "precision": null,
      "scale": null,
      "mysql": {
        "columnName": "logo",
        "dataType": "longtext",
        "dataLength": 4294967295,
        "dataPrecision": null,
        "dataScale": null,
        "nullable": "N"
      }
    },
    "billuppertext": {
      "type": "string",
      "required": false,
      "length": 4294967295,
      "precision": null,
      "scale": null,
      "mysql": {
        "columnName": "billUpperText",
        "dataType": "longtext",
        "dataLength": 4294967295,
        "dataPrecision": null,
        "dataScale": null,
        "nullable": "N"
      }
    },
    "createdon": {
      "type": "date",
      "required": true,
      "length": null,
      "precision": null,
      "scale": null,
      "mysql": {
        "columnName": "createdOn",
        "dataType": "timestamp",
        "dataLength": null,
        "dataPrecision": null,
        "dataScale": null,
        "nullable": "N"
      }
    },
    "modifiedon": {
      "type": "date",
      "required": true,
      "length": null,
      "precision": null,
      "scale": null,
      "mysql": {
        "columnName": "modifiedOn",
        "dataType": "timestamp",
        "dataLength": null,
        "dataPrecision": null,
        "dataScale": null,
        "nullable": "N"
      }
    }
  },
  "validations": [],
  "relations": {},
  "acls": [
    {
      "accessType": "*",
      "principalType": "ROLE",
      "principalId": "admin",
      "permission": "ALLOW"
    },
    {
      "accessType": "*",
      "principalType": "ROLE",
      "principalId": "$everyone",
      "permission": "DENY"
    }
  ],
  "methods": {}
}
